{
    "type": "createdieselgenerators:basin_fermenting",
    "ingredients": [
        {
            "type": "fluid_stack",
            "fluid": "create:potion",
            "amount": 250,
            "components": {
                "minecraft:potion_contents": {
                    "potion": "minecraft:regeneration"
                }
            }
        },
        {
            "item": "minecraft:redstone"
        }
    ],
    "processing_time": 150,
    "results": [
        {
            "id": "create:potion",
            "amount": 250,
            "components": {
                "minecraft:potion_contents": {
                    "potion": "minecraft:long_regeneration"
                }
            }
        }
    ]
}